README.rst
setup.py
django_mail_utils.egg-info/PKG-INFO
django_mail_utils.egg-info/SOURCES.txt
django_mail_utils.egg-info/dependency_links.txt
django_mail_utils.egg-info/requires.txt
django_mail_utils.egg-info/top_level.txt
mail_utils/__init__.py
mail_utils/messages.py