Metadata-Version: 1.1
Name: django-mail-utils
Version: 0.2
Summary: Django mail mixins and utilities
Home-page: https://github.com/koorgoo/django-mail-utils/
Author: Dima Kurguzov
Author-email: koorgoo@gmail.com
License: MIT
Platform: UNKNOWN
Classifier: Programming Language :: Python
Classifier: Environment :: Web Environment
Classifier: Framework :: Django
Classifier: Programming Language :: Python :: 2.7
Classifier: Programming Language :: Python :: 3.3
